ctfr/__init__.py
ctfr/ctfr_data.py
ctfr/ctfr_losses.py
ctfr/ctfr_losses_bkp.py
ctfr/ctfr_models.py
ctfr/ctfr_models_v0.1.29.py
ctfr/ctfr_models_v0.1.31.py
ctfrv2/__init__.py
ctfrv2/ctfrv2_data.py
ctfrv2/ctfrv2_global_scaled_data.py
ctfrv2/ctfrv2_losses.py
ctfrv2/ctfrv2_models.py
ctfrv2_gpu/__init__.py
ctfrv2_gpu/ctfrv2_data_gpu.py
ctfrv2_gpu/ctfrv2_losses_gpu.py
ctfrv2_gpu/ctfrv2_model_gpu.py
eda/__init__.py
eda/eda_lib.py
eda/eda_lib_v0.1.18.py
eda/eda_lib_v0.1.19.py
eda/eda_lib_v0.1.37.py
sage/__init__.py
sage/sage_data.py
sage/sage_data_old.py
sage/sage_global_scaled_data_old.py
sage/sage_losses.py
sage/sage_losses_old.py
sage/sage_model.py
sage/sage_model_old.py
sage_gpu/__init__.py
sage_gpu/sage_data_gpu.py
sage_gpu/sage_losses_gpu.py
sage_gpu/sage_model_gpu.py
sage_gpu/sage_model_gpu_v1.2.3.py
stctn/__init__.py
stctn/stctn_data.py
stctn/stctn_losses.py
stctn/stctn_losses_bkp.py
stctn/stctn_models.py
tfr/__init__.py
tfr/tfr_data.py
tfr/tfr_data_v0.1.11.py
tfr/tfr_data_v0.1.12.py
tfr/tfr_data_v0.1.14.py
tfr/tfr_data_v0.1.15.py
tfr/tfr_data_v0.1.16.py
tfr/tfr_data_v0.1.18.py
tfr/tfr_data_v0.1.21.py
tfr/tfr_local_block_sparse_attention.py
tfr/tfr_local_block_sparse_attention_v0.1.10.py
tfr/tfr_local_block_sparse_attention_v0.1.12.py
tfr/tfr_losses.py
tfr/tfr_losses_bkp.py
tfr/tfr_models.py
tfr/tfr_models_v0.1.10.py
tfr/tfr_models_v0.1.11.py
tfr/tfr_models_v0.1.23.py
tfr/tfr_models_v0.1.31.py
tft/__init__.py
tft/tft_data.py
tft/tft_data_old.py
tft/tft_data_v1.1.3.py
tft/tft_data_v1.1.7.py
tft/tft_global_scaled_data.py
tft/tft_losses.py
tft/tft_model.py
tft/tft_model_v0.1.26.py
tft/tft_model_v0.1.31.py
tft/tft_model_v1.1.3.py
tft_gpu/__init__.py
tft_gpu/tft_data_gpu.py
tft_gpu/tft_losses_gpu.py
tft_gpu/tft_model_gpu.py
fmldk-1.2.5.dist-info/METADATA
fmldk-1.2.5.dist-info/WHEEL
fmldk-1.2.5.dist-info/top_level.txt
fmldk-1.2.5.dist-info/RECORD
