Metadata-Version: 2.1
Name: fmldk
Version: 1.2.5
Summary: Forecast ML library
Author: Rahul Sinha
Author-email: rahul.sinha@unilever.com
Requires-Dist: tensorflow
Requires-Dist: tensorflow-probability
Requires-Dist: numpy
Requires-Dist: statsmodels
Requires-Dist: pandas
Requires-Dist: joblib
Requires-Dist: pathlib
Requires-Dist: bokeh
Requires-Dist: holoviews
Requires-Dist: hvplot
Requires-Dist: ennemi
